spacy_langdetect/__init__.py
spacy_langdetect/spacy_langdetect.py
spacy_langdetect-0.1.1.dist-info/DESCRIPTION.rst
spacy_langdetect-0.1.1.dist-info/METADATA
spacy_langdetect-0.1.1.dist-info/RECORD
spacy_langdetect-0.1.1.dist-info/WHEEL
spacy_langdetect-0.1.1.dist-info/metadata.json
spacy_langdetect-0.1.1.dist-info/top_level.txt
tests/__init__.py
tests/test_spacy_langdetect.py
