Metadata-Version: 2.0
Name: spacy-langdetect
Version: 0.1.1
Summary: Fully customizable language detection pipeline for spaCy
Home-page: https://github.com/Abhijit-2592/spacy-langdetect
Author: Abhijit Balaji
Author-email: balaabhijit5@gmail.com
License: UNKNOWN
Platform: UNKNOWN
Classifier: Programming Language :: Python :: 3
Classifier: License :: OSI Approved :: MIT License
Classifier: Operating System :: OS Independent
Requires-Dist: langdetect (==1.0.7)
Requires-Dist: pytest
